iceman/__init__.py
iceman/configuration.py
iceman/interceptor.cfg
iceman/interceptor.py
iceman/crypto_strategies/__init__.py
iceman/crypto_strategies/fernet.py
iceman/crypto_strategies/icemicro.py
iceman/crypto_strategies/null.py
iceman/crypto_strategies/strategy.py
iceman/traffic/__init__.py
iceman/traffic/traffic.py
iceman/traffic/traffic_null.py
iceman-0.3.4.data/scripts/iceman
iceman-0.3.4.dist-info/DESCRIPTION.rst
iceman-0.3.4.dist-info/METADATA
iceman-0.3.4.dist-info/RECORD
iceman-0.3.4.dist-info/WHEEL
iceman-0.3.4.dist-info/metadata.json
iceman-0.3.4.dist-info/top_level.txt
tests/__init__.py
tests/profile_icecore.py
tests/raw_socket_echo.py
tests/test_configuration.py
tests/test_iceman.py
tests/test_interceptor.py
tests/crypto_strategies/__init__.py
tests/crypto_strategies/test_fernet.py
tests/crypto_strategies/test_icemicro.py
tests/crypto_strategies/test_strategy.py
tests/traffic/__init__.py
tests/traffic/test_traffic.py
